pyrdo/__init__.py
pyrdo/array.py
pyrdo/base.py
pyrdo/dict.py
pyrdo/list.py
pyrdo/main.py
pyrdo/seq.py
pyrdo/set.py
pyrdo/sys.py
pyrdo/tuple.py
pyrdo/value.py
pyrdo/vector.py
pyrdo-1.5.2.dist-info/LICENSE
pyrdo-1.5.2.dist-info/METADATA
pyrdo-1.5.2.dist-info/WHEEL
pyrdo-1.5.2.dist-info/top_level.txt
pyrdo-1.5.2.dist-info/RECORD
